betfair_python_rest/__init__.py
betfair_python_rest/api_exceptions/__init__.py
betfair_python_rest/api_exceptions/base_exception.py
betfair_python_rest/api_exceptions/exception_enum.py
betfair_python_rest/enums/__init__.py
betfair_python_rest/enums/base.py
betfair_python_rest/enums/accounts/__init__.py
betfair_python_rest/enums/accounts/affiliate_relation_status.py
betfair_python_rest/enums/accounts/grant_type.py
betfair_python_rest/enums/accounts/include_item.py
betfair_python_rest/enums/accounts/item_class.py
betfair_python_rest/enums/accounts/status.py
betfair_python_rest/enums/accounts/subscription_status.py
betfair_python_rest/enums/accounts/token_type.py
betfair_python_rest/enums/accounts/wallet.py
betfair_python_rest/enums/accounts/win_lose.py
betfair_python_rest/enums/betting/__init__.py
betfair_python_rest/enums/betting/bet_status.py
betfair_python_rest/enums/betting/bet_target_type.py
betfair_python_rest/enums/betting/execution_report_error_code.py
betfair_python_rest/enums/betting/execution_report_status.py
betfair_python_rest/enums/betting/group_by.py
betfair_python_rest/enums/betting/instruction_report_error_code.py
betfair_python_rest/enums/betting/instruction_report_status.py
betfair_python_rest/enums/betting/market_betting_type.py
betfair_python_rest/enums/betting/market_projection.py
betfair_python_rest/enums/betting/market_sort.py
betfair_python_rest/enums/betting/market_status.py
betfair_python_rest/enums/betting/match_projection.py
betfair_python_rest/enums/betting/order_by.py
betfair_python_rest/enums/betting/order_projection.py
betfair_python_rest/enums/betting/order_status.py
betfair_python_rest/enums/betting/order_type.py
betfair_python_rest/enums/betting/persistence_type.py
betfair_python_rest/enums/betting/price_data.py
betfair_python_rest/enums/betting/price_ladder_type.py
betfair_python_rest/enums/betting/rollup_model.py
betfair_python_rest/enums/betting/runner_status.py
betfair_python_rest/enums/betting/side.py
betfair_python_rest-0.13.dist-info/METADATA
betfair_python_rest-0.13.dist-info/WHEEL
betfair_python_rest-0.13.dist-info/top_level.txt
betfair_python_rest-0.13.dist-info/RECORD
