Metadata-Version: 2.1
Name: betfair-python-rest
Version: 0.13
Summary: Python package of REST API managers (Betting and Accounts APIs)
Home-page: https://github.com/Sibiryakanton/betfair_python_rest
Author: Anton Igin
Author-email: antonigin1995@gmail.com
License: UNKNOWN
Project-URL: Source, https://github.com/Sibiryakanton/betfair_python_rest
Platform: UNKNOWN
Classifier: Programming Language :: Python :: 3
Requires-Python: >=3.6
Requires-Dist: requests (==2.22.0)
Requires-Dist: dataclasses (==0.6)
